{
  "next_project_number": 111,
  "active_projects": [
    {
      "project_number": 110,
      "project_name": "frame_class_validation",
      "status": "not_started",
      "task_type": "python",
      "created": "2026-06-01T00:00:00Z",
      "last_updated": "2026-06-01T00:00:00Z",
      "dependencies": [
        100
      ]
    },
    {
      "project_number": 109,
      "project_name": "cross_oracle_differential_testing",
      "status": "not_started",
      "task_type": "python",
      "created": "2026-06-01T00:00:00Z",
      "last_updated": "2026-06-01T00:00:00Z",
      "dependencies": [
        103
      ]
    },
    {
      "project_number": 108,
      "project_name": "soundness_regression_test_suite",
      "status": "not_started",
      "task_type": "python",
      "created": "2026-06-01T00:00:00Z",
      "last_updated": "2026-06-01T00:00:00Z",
      "dependencies": [
        103
      ]
    },
    {
      "project_number": 107,
      "project_name": "boundary_temporal_depth_mitigation",
      "status": "not_started",
      "task_type": "python",
      "created": "2026-06-01T00:00:00Z",
      "last_updated": "2026-06-01T00:00:00Z",
      "dependencies": [
        102
      ]
    },
    {
      "project_number": 106,
      "project_name": "architecture_review_refactor",
      "status": "completed",
      "task_type": "python",
      "created": "2026-05-30T12:30:00Z",
      "last_updated": "2026-06-01T00:00:00Z",
      "session_id": "sess_1780208200_22f2ee",
      "researched": "2026-05-31T06:13:51Z",
      "next_artifact_number": 5,
      "completion_summary": "Produced architectural decision record (ADR) with 9 decisions capturing three-repo architecture, zero code-level dependency, two-layer package structure, boundary buffer mitigation, ternary serialization, and empirical soundness strategy. Rewrote task descriptions for 100-105 with specific file references and acceptance criteria. Created 4 new tasks (107-110) covering boundary analysis, soundness regression tests, cross-oracle differential testing, and frame class validation. Updated dependency graph and confirmed DAG with wave structure enabling maximum parallelism.",
      "artifacts": [
        {
          "path": "specs/106_architecture_review_refactor/reports/01_team-research.md",
          "type": "research",
          "summary": "Team research with 4 teammates"
        },
        {
          "path": "specs/106_architecture_review_refactor/reports/02_team-research.md",
          "type": "research",
          "summary": "Team research with 4 teammates: BimodalLogic alignment and soundness architecture"
        },
        {
          "path": "specs/106_architecture_review_refactor/reports/03_clean-break-architecture.md",
          "type": "research",
          "summary": "Clean-break architecture design research"
        },
        {
          "path": "specs/106_architecture_review_refactor/plans/03_implementation-plan.md",
          "type": "plan",
          "summary": "5-phase plan to update task descriptions 99-105, create 4 new tasks (107-110), produce architectural decision record, and update dependency graph"
        },
        {
          "path": "specs/106_architecture_review_refactor/reports/04_architectural-decisions.md",
          "type": "research",
          "summary": "Architectural decision record: 9 decisions, pipeline diagram, keep/drop/fix inventory, dependency graph"
        }
      ]
    },
    {
      "project_number": 100,
      "project_name": "strip_non_bimodal_code",
      "status": "completed",
      "task_type": "python",
      "created": "2026-05-30T12:00:00Z",
      "last_updated": "2026-06-01T16:00:00Z",
      "session_id": "sess_1780208200_22f2ee",
      "completion_summary": "Stripped all non-bimodal code from ModelChecker: deleted logos/, iterate/, jupyter/, output/notebook/ directories (203 files), fixed 13 hard coupling points, removed bimodal/iterate.py dependency, updated 25+ test files, removed networkx/jupyter/cvc5 dependencies from pyproject.toml. Gate: 171 of 172 expected tests pass (BM_CM_1 pre-existing timeout issue unrelated to changes).",
      "researched": "2026-06-01T00:00:00Z",
      "planned": "2026-06-01T12:00:00Z",
      "next_artifact_number": 3,
      "plan_metadata": {
        "phases": 6,
        "total_effort_hours": 4,
        "complexity": "medium",
        "research_integrated": true,
        "plan_version": 1,
        "dependency_waves": [
          [
            1
          ],
          [
            2
          ],
          [
            3
          ],
          [
            4
          ],
          [
            5
          ],
          [
            6
          ]
        ],
        "reports_integrated": [
          {
            "path": "reports/01_codebase-audit.md",
            "integrated_in_plan_version": 1,
            "integrated_date": "2026-06-01"
          }
        ]
      },
      "artifacts": [
        {
          "path": "specs/100_strip_non_bimodal_code/reports/01_codebase-audit.md",
          "type": "research",
          "summary": "Complete codebase audit: files to delete, coupling points with line refs, dependency analysis, risk assessment, and test baseline"
        },
        {
          "path": "specs/100_strip_non_bimodal_code/plans/02_implementation-plan.md",
          "type": "plan",
          "summary": "6-phase implementation plan: fix coupling, remove iterate dep, delete modules, clean refs, clean tests, clean dependencies"
        },
        {
          "path": "specs/100_strip_non_bimodal_code/summaries/02_strip-non-bimodal-summary.md",
          "type": "summary",
          "summary": "Implementation summary: 6 phases completed, 203+ files deleted, 171 tests passing"
        }
      ]
    },
    {
      "project_number": 101,
      "project_name": "restructure_pip_package",
      "status": "completed",
      "task_type": "python",
      "created": "2026-05-30T12:00:00Z",
      "last_updated": "2026-06-01T09:35:00Z",
      "next_artifact_number": 2,
      "plan_metadata": {
        "phases": 4,
        "total_effort_hours": 2.5,
        "complexity": "medium",
        "research_integrated": true,
        "plan_version": 1,
        "dependency_waves": [
          [
            1
          ],
          [
            2
          ],
          [
            3
          ],
          [
            4
          ]
        ],
        "reports_integrated": [
          {
            "path": "reports/01_restructure-research.md",
            "integrated_in_plan_version": 1,
            "integrated_date": "2026-06-01"
          }
        ]
      },
      "completion_summary": "Restructured as bimodal-logic pip package: overhauled pyproject.toml metadata, created thin bimodal_logic/ facade with 4 stub files, cleaned up stale egg-info, verified editable install and all imports work. Bimodal test suite: 171 pass, 1 pre-existing failure (BM_CM_1)."
    },
    {
      "project_number": 102,
      "project_name": "formula_json_translation",
      "status": "not_started",
      "task_type": "python",
      "created": "2026-05-30T12:00:00Z",
      "last_updated": "2026-05-30T23:55:00Z"
    },
    {
      "project_number": 103,
      "project_name": "oracle_provider_implementation",
      "status": "not_started",
      "task_type": "python",
      "created": "2026-05-30T12:00:00Z",
      "last_updated": "2026-05-30T23:55:00Z"
    },
    {
      "project_number": 104,
      "project_name": "programmatic_api_cleanup",
      "status": "not_started",
      "task_type": "python",
      "created": "2026-05-30T12:00:00Z",
      "last_updated": "2026-05-30T23:55:00Z"
    },
    {
      "project_number": 105,
      "project_name": "integration_testing_validation",
      "status": "not_started",
      "task_type": "python",
      "created": "2026-05-30T12:00:00Z",
      "last_updated": "2026-05-30T23:55:00Z"
    }
  ],
  "repository_health": {
    "last_assessed": "2026-05-31T01:11:13Z",
    "todo_count": 16,
    "fixme_count": 0,
    "build_errors": 0,
    "status": "healthy"
  }
}
